coveragespace/__init__.py
coveragespace/api.py
coveragespace/cache.py
coveragespace/cli.py
coveragespace/coverage.py
coveragespace/environments.py
coveragespace/repository.py
coveragespace/tests/__init__.py
coveragespace/tests/conftest.py
coveragespace/tests/test_cache.py
coveragespace/tests/test_cli.py
coveragespace/tests/test_coverage.py
coveragespace/tests/test_environments.py
coveragespace/tests/test_repository.py
coveragespace-6.1.dist-info/LICENSE.md
coveragespace-6.1.dist-info/METADATA
coveragespace-6.1.dist-info/WHEEL
coveragespace-6.1.dist-info/entry_points.txt
coveragespace-6.1.dist-info/RECORD
