Metadata-Version: 2.1
Name: coveragespace
Version: 6.1
Summary: A place to track your code coverage metrics.
Home-page: https://coverage.space/client/
License: MIT
Keywords: coverage,testing,command-line
Author: Jace Browning
Author-email: jacebrowning@gmail.com
Requires-Python: >=3.8,<4.0
Classifier: Development Status :: 5 - Production/Stable
Classifier: Environment :: Console
Classifier: Intended Audience :: Developers
Classifier: License :: OSI Approved :: MIT License
Classifier: Natural Language :: English
Classifier: Operating System :: OS Independent
Classifier: Programming Language :: Python
Classifier: Programming Language :: Python :: 3
Classifier: Programming Language :: Python :: 3.8
Classifier: Programming Language :: Python :: 3.9
Classifier: Programming Language :: Python :: 3.10
Classifier: Programming Language :: Python :: 3.11
Classifier: Programming Language :: Python :: 3.12
Classifier: Topic :: Software Development
Classifier: Topic :: Software Development :: Quality Assurance
Classifier: Topic :: Software Development :: Testing
Requires-Dist: colorama (>=0.4)
Requires-Dist: coverage (>=4.0)
Requires-Dist: docopt (>=0.6)
Requires-Dist: minilog (>=2.0)
Requires-Dist: requests (>=2.28,<3.0)
Project-URL: Documentation, https://cli.coverage.space
Project-URL: Repository, https://github.com/jacebrowning/coverage-space-cli
